matr/__init__.py
matr/_modidx.py
matr/core.py
matr/inst.py
matr-0.0.10.dist-info/LICENSE
matr-0.0.10.dist-info/METADATA
matr-0.0.10.dist-info/WHEEL
matr-0.0.10.dist-info/entry_points.txt
matr-0.0.10.dist-info/top_level.txt
matr-0.0.10.dist-info/RECORD
