Metadata-Version: 2.1
Name: matr
Version: 0.0.10
Summary: matr (module attribute)
Home-page: https://github.com/dsm-72/matr
Author: dsm-72
Author-email: sumner.magruder@yale.edu
License: Apache Software License 2.0
Keywords: matr import try except importlib module attribute dynamic attr asset
Classifier: Development Status :: 4 - Beta
Classifier: Intended Audience :: Developers
Classifier: Natural Language :: English
Classifier: Programming Language :: Python :: 3.11
Classifier: License :: OSI Approved :: Apache Software License
Requires-Python: >=3.11
License-File: LICENSE
Requires-Dist: nchr
Requires-Dist: nlit
Requires-Dist: pdec
Requires-Dist: itry
Provides-Extra: dev
